requirements.txt
setup.py
django_configurations_celery_app/__init__.py
django_configurations_celery_app.egg-info/PKG-INFO
django_configurations_celery_app.egg-info/SOURCES.txt
django_configurations_celery_app.egg-info/dependency_links.txt
django_configurations_celery_app.egg-info/requires.txt
django_configurations_celery_app.egg-info/top_level.txt